to7z/__init__.py
to7z/__main__.py
to7z/cli.py
to7z/rich_console.py
to7z/to7z.py
to7z-1.3.9.dist-info/entry_points.txt
to7z-1.3.9.dist-info/WHEEL
to7z-1.3.9.dist-info/METADATA
to7z-1.3.9.dist-info/RECORD
