Metadata-Version: 2.1
Name: to7z
Version: 1.3.9
Summary: Converts ZIP to 7z.
Author: Marcus Bruno Fernandes Silva
Author-email: marcusbfs@gmail.com
Requires-Python: >=3.8,<4.0
Classifier: Programming Language :: Python :: 3
Classifier: Programming Language :: Python :: 3.8
Classifier: Programming Language :: Python :: 3.9
Requires-Dist: click (>=8.0.1,<9.0.0)
Requires-Dist: py7zr (>=0.16.1,<0.17.0)
Requires-Dist: rich (>=10.2.2,<11.0.0)
